{"3WfC5Nh11u5zu2IqUza1tg==":"990677939233802240117-561x128.png","Zi4Lww5+b6J4FVNRRqOYFw==":"1238813170313902240117-623x128.png","GvIgMw2HLIsPukNzBWk7MA==":"423548522274002240117-678x128.png","j+HhzTRwCXmcL3OrXp8HkQ==":"blog%20crown-201x128.png","nuBpZ+UpQmtOVC5GHJ3cQQ==":"pink-princess-crowns-logo-admhz5-clipart-210x128.png","rY0hRU2fC2ReHwkAAtxy2g==":"blog%20crown-128x81.png","fX6jQSQ5+bJUGX7jVwqSAQ==":"mbr-2000x1324.jpg","MmqcWVmhfTktkjmB8KH8tA==":"mbr-2000x1333.jpg","nS5q6xjbvMy4aWa7G7t7QA==":"mbr-2000x1335.jpg","sBt9pWPwyhVsODjKaCme5g==":"mbr-1-2000x1324.jpg","Y2jXQSQr4QRCg1SWh42sYw==":"mbr-1-2000x1333.jpg","x0gW5Ym4hlaLh5ayCGJzfA==":"mbr-2-2000x1333.jpg","F3nDHkL7vtGPNl/n9eSpbw==":"wynwood%20poster%20final%20-2000x2957.jpg","VP+DcTk09Dqm0JH+e4QL2Q==":"final%2060s-2000x3529.jpg","SbcZiZwx5XMEK4dmR9rJaA==":"final%2060s-2000x3529.jpg","ZlK+QTi/74xY7y9W4hWqrw==":"giuliana%20r-2000x1990.jpg","7H+y90Kl298OjuWYiP1AHQ==":"repair-before-2000x2500.jpg","0w4KfTV+mdEQ8Uz0dk347w==":"repair-after-2000x2500.jpg","ITXfm6MMRX5TrJ8At5AYEQ==":"wynwood%20poster%20final%20-2000x2957.jpg","HKFyM8XDivIQaryhmY4jdg==":"orch%20poster-2000x2962.jpg","MPaCk9UfYwKkCzGl+Y9nDw==":"room-2000x1454.jpg","pHS53W7wd/jve0szskVVwg==":"jetson-2000x1454.jpg","LT6ntwX2qAezwD8azFag6A==":"phone%20case-2000x1454.jpg","vgUVLM5m9bG381DE83Kiiw==":"mpop-2000x2750.jpg","nCWhS9IArxm88Bpo86FbzQ==":"wynwood-2000x2750.jpg","tG5mdg/zpyNHFmUbMS+uzw==":"repar-2000x1375.jpg","ZlhL9+HfCzZtcI4BoEkTSA==":"logo-2000x2000.jpg","PVNLtBLBSbrvP0wXkXFsXw==":"mdcps%20logo%204x4-2000x2150.jpg","e4DK1vNq7x/+BOU7oKD7ZQ==":"dream-2000x2750.jpg","Ll4jkMcJCr9rENtJDzPBWQ==":"mas%20-2000x2750.jpg","MpLq48ylHO4snFKhknUc+Q==":"clip-2000x1454.jpg","cp1iHDzQQmjYsJNS6sQFtA==":"mbr-2000x1333.jpg","nAxkK6wIEhuvrCAVnvvS9A==":"mbr-2000x3000.jpg","JgtXIfvwdHF/gP9G1XAFQg==":"mbr-1-2000x1333.jpg","a/e1L37slxxISPfOsKx1zw==":"mbr-3-2000x1333.jpg","9wgV0b+9+fUHYqz7T2cSHw==":"signature%20no%20background-290x128.jpg","d/edJ82//6UOpJnTfvoeRw==":"mbr-4-2000x1333.jpg","/KGL7Q7GFud0h2ow23ZGMg==":"mbr-2000x1500.jpg","YXNMBylouBi6DPZD/NgV7Q==":"mbr-2000x1125.jpg","/lCNFKVNDItL4y7zowK+KA==":"mbr-2000x1046.jpg","oF2rXXnVHG7U3yG5L3yi0w==":"mbr-2000x1334.jpg","z9tOo1Tgm9PZkBga7/yNEw==":"mbr-5-2000x1333.jpg","Yg8hGO9w7wtLDnCLKawgDw==":"mbr-2000x1336.jpg","dHL6DxNeX5SE5PpcASWpvQ==":"signature_5wctklnsyy55kq9p3b-312x128.png","g1L39rQ5BuakKXqe8qaRXg==":"1799186584213200117-673x128.png","uadh+brchn+aJKN22qfIdA==":"mbr-192x128.jpg","zbW3KKhFWogmNA9g9juOUg==":"mbr-1-2000x1125.jpg","Ue5ne856nod9U9yaBkxuRw==":"mbr-6-2000x1333.jpg","8Gbj73xy7ljGkkUk4uv92A==":"dscf0200-1400x1050.jpg","WFwGf1kzQhcRFHh+/6MOlQ==":"mbr-7-2000x1333.jpg","TInyd3ZHzrW1cC1ODE6Unw==":"dream-1-2000x2750.jpg","lny5zjcvQfWoJciNMNFYzg==":"goodle%20doodle-%20giuliana%20ramirez-2000x1010.jpg","DpFQORsvQRCxmCDHnMM0vg==":"mbr-8-2000x1333.jpg","LFi2lq1/I9zutasfSDTMCQ==":"mbr-2000x1326.jpg","tkImHT3dYEme2etTy9Sn/A==":"114180-pink-glitter-pattern--2000x1204.jpg","QfWT5f/eJE9DUK2Q2eYfJg==":"download-2000x1120.jpg","4lApag3fyRO5E1LAtk4gYw==":"mbr-2000x1339.jpg","eSliLF/lYAMgoVHN5BKbPQ==":"mbr-9-2000x1333.jpg"}